{
  "project_info": {
    "project_number": "964930490684",
    "firebase_url": "https://flapp-meme-default-rtdb.firebaseio.com",
    "project_id": "flapp-meme",
    "storage_bucket": "flapp-meme.firebasestorage.app"
  },
  "client": [
    {
      "client_info": {
        "mobilesdk_app_id": "1:964930490684:android:2a346f8c6f0fb8a0d98e39",
        "android_client_info": {
          "package_name": "com.flapp.meme"
        }
      },
      "oauth_client": [
        {
          "client_id": "964930490684-ubf9g0ukaohobe64f4buofvpc9raqgns.apps.googleusercontent.com",
          "client_type": 1,
          "android_info": {
            "package_name": "com.flapp.meme",
            "certificate_hash": "8f8eeaf1df94248fde5467419932c6eaa218798b"
          }
        },
        {
          "client_id": "964930490684-m6gkfmnsufrg6l1uqehjdq2sllqo0nii.apps.googleusercontent.com",
          "client_type": 3
        }
      ],
      "api_key": [
        {
          "current_key": "AIzaSyA2GpuEbzU53UbLZgzT1kSg2srY2QHZP4Y"
        }
      ],
      "services": {
        "appinvite_service": {
          "other_platform_oauth_client": [
            {
              "client_id": "964930490684-m6gkfmnsufrg6l1uqehjdq2sllqo0nii.apps.googleusercontent.com",
              "client_type": 3
            }
          ]
        }
      }
    }
  ],
  "configuration_version": "1"
}